dbrew/__init__.py
dbrew/py.typed
dbrew/client/__init__.py
dbrew/client/cli.py
dbrew/core/__init__.py
dbrew/core/validate/__init__.py
dbrew/core/validate/schema.py
dbrew-0.0.3.dist-info/LICENSE
dbrew-0.0.3.dist-info/METADATA
dbrew-0.0.3.dist-info/WHEEL
dbrew-0.0.3.dist-info/entry_points.txt
dbrew-0.0.3.dist-info/top_level.txt
dbrew-0.0.3.dist-info/RECORD
