Metadata-Version: 2.1
Name: dbrew
Version: 0.0.3
Summary: Brew and orchestrate your data products seamlessly into actionable deployments with DBrew, the CLI tool tailored for modern data maestros.
Home-page: https://github.com/somasays/dbrew
Author: Somasundaram S
Author-email: "Somasundaram S" <somasundaram@outlook.com>
License: MIT License
Classifier: License :: OSI Approved :: MIT License
Requires-Python: >=3.9
License-File: LICENSE
Requires-Dist: pydantic >=2.4.2
Requires-Dist: pyyaml >=6.0.1
Requires-Dist: click >=8.1.7
